proxiesdotcom/__init__.py
proxiesdotcom/proxiesdotcom.py
proxiesdotcom/models/__init__.py
proxiesdotcom/models/base_proxy.py
proxiesdotcom/models/proxy.py
proxiesdotcom-0.0.4.dist-info/METADATA
proxiesdotcom-0.0.4.dist-info/WHEEL
proxiesdotcom-0.0.4.dist-info/top_level.txt
proxiesdotcom-0.0.4.dist-info/RECORD
