Metadata-Version: 2.1
Name: proxiesdotcom
Version: 0.0.4
Summary: proxiesdotcom
Home-page: https://github.com/kkristof200/py_proxies_dot_com
Author: Kristof
License: UNKNOWN
Platform: UNKNOWN
Classifier: Programming Language :: Python :: 3
Classifier: License :: OSI Approved :: MIT License
Classifier: Operating System :: OS Independent
Requires-Python: >=3.5
Requires-Dist: requests
Requires-Dist: jsoncodable
Requires-Dist: ksimpleapi
Requires-Dist: kcu
Requires-Dist: beautifulsoup4
